refaclass/__init__.py
refaclass/base.py
refaclass/exceptions.py
refaclass/main.py
refaclass/settings.py
refaclass/core/__init__.py
refaclass/core/detection.py
refaclass/core/executor.py
refaclass/core/model.py
refaclass/core/outliers.py
refaclass/core/relation.py
refaclass/output/color.py
refaclass/output/outputs.py
refaclass/preprocess/__init__.py
refaclass/preprocess/argument_handler.py
refaclass/preprocess/class_handler.py
refaclass/preprocess/source_code_reader.py
refaclass-2.3.0.dist-info/LICENSE
refaclass-2.3.0.dist-info/METADATA
refaclass-2.3.0.dist-info/WHEEL
refaclass-2.3.0.dist-info/entry_points.txt
refaclass-2.3.0.dist-info/top_level.txt
refaclass-2.3.0.dist-info/RECORD
