Metadata-Version: 2.1
Name: refaclass
Version: 2.3.0
Summary: A Python package for RefaClass
Home-page: https://github.com/hirokazuniimoto/refa-class
Author: Hirokazu Niimoto
License: MIT
Classifier: Programming Language :: Python
Classifier: Programming Language :: Python :: 3.8
Classifier: License :: OSI Approved :: MIT License
License-File: LICENSE
Requires-Dist: fasttext (==0.9.2)
Requires-Dist: gdown (==4.7.1)
Requires-Dist: gensim (==4.3.2)
Requires-Dist: joblib (==1.3.2)
Requires-Dist: numpy (==1.24.4)
Requires-Dist: pandas (==2.0.3)
Requires-Dist: pybind11 (==2.11.1)
Requires-Dist: pyclustering (==0.10.1.2)
Requires-Dist: python-dateutil (==2.8.2)
Requires-Dist: pytz (==2023.3)
Requires-Dist: scikit-learn (==1.3.0)
Requires-Dist: scipy (==1.10.1)
Requires-Dist: six (==1.16.0)
Requires-Dist: threadpoolctl (==3.2.0)
Requires-Dist: tzdata (==2023.3)
Requires-Dist: tqdm (==4.66.1)
